Workbook

Sheet README
B3: Please contact Bart Lorang (lorangb@gmail.com or 303.717.0414) to discuss this model and walk through it.
B5: Instructions
B6: -Cells in Yellow are Assumptions, where feasible, sources are noted
B7: *Net Present Value is calculated based on CEMEX's WACC from their public financials. This is how public company finance departments (partiuclarly mining organizations) evaluate projects
B8: *Proposal Matrix sheet Stacks up the Town of Lyons Proposal vs. current options on the table
B10: Disclaimers
B11: * This is an outside-in financial pro-forma based on a wide range of assumptions.
B12: * If there's a bug in a formula, or something needs to be cleaned up, please don't hesitate to make it happen
B13: * Everything isn't perfect, this is all "v0.1"
B14: * Water Rights information if highly speculative at best, and is sourced from a 1977 Mining Reclamation Plan document detailing CEMEX's water rights south of HWY 66

Sheet NPVs & Pro-Formas
B2: Summary - Value to Shareholders for CEMEX | C2: Net Present Value | D2: CEMEX's Preference
B3: =B60 -> Option A - Stop Mining, Operate "Plant Indefinitely" | C3: =C94 -> -3237342.5 | D3: 4
B4: =B100 -> Option B - Operate 15 Years, then Shut Down, Sell to BoCo | C4: =C131 -> 64432187 | D4: 1
B5: =B135 -> Option C - Operate 5 Years, Land Conserved, Purchase Options to Boulder/Lyons | C5: =C174 -> 40720124 | D5: 2
B6: =B178 -> Option D - Stop Mining If Permit Denied, Sell Off All Assets | C6: =C178 -> 23291773 | D6: 3
B8: Key Assumptions
B10: Capital Costs
B11: Discount Rate (WACC) for CEMEX | C11: 0.145 | D11: <-- from https://finbox.com/NYSE:CX/explorer/wacc
B13: Reclamation & Cleanup Costs
B14: Dowe Flats Reclamation Costs | C14: -12683299 | D14: <-- from surety bonds (https://drms.colorado.gov/search-by-county)
B15: Cement Mine/Plant Reclamation Costs ("Lyons Quarry") | C15: -8953127 | D15: <-- surety bonds (https://drms.colorado.gov/search-by-county)
B16: CEMEX Sandstone Quarry Reclamation Costs | C16: -409366 | D16: <-- from surety bonds (https://drms.colorado.gov/search-by-county)
B17: CEMEX Plant Demolition Costs (Additional above and beyond 20 year old estimates) | C17: -15000000 | D17: <-- need to estimate what it would cost to safely tear it down and haul it away
B19: Production & Raw Materials Assumptions
B20: Tons of Limestone Trucked In Per Year (from Unknown Location) | C20: 250000 | D20: <~ according to applicants (confusing) testimony, this is happening already at 300,0i00 (assume 250K limestone and 50K shale?)
B21: Tons of Limestone Dowe Flats Produces Per Year | C21: 50000 | D21: < -- assumption based on CEMEX (confusing) testimony
B22: Tons of Shale Dowe Flats Produces Per Year | C22: 350000 | D22: <--400,000 per year according to CEMEX (although CEMEX SU-22-003 application had <300,000 per year) Applicant Testified at 350,000 - 450,000
B23: Tons of Silica Hauled from Silica Quarry | C23: 35000 | D23: <-- from CEMEX Application SU-22-003
B24: Ratio of Raw Material (Limestone, Shale) for 1 Ton of Cement | C24: 1.7 | D24: <-- from research of typical ratios
B25: Implied Tons of Cement Per Year (based on Limestone+Silica+Shale) | C25: 338475 | D25: <-- calculation/estimate - other data from https://www.sec.gov/Archives/edgar/data/1076378/000119312522133730/0001193125-22-133730-index.html indicates 338,475 in 2021
B26: Total Raw Material Tonnage (Limestone, Shale and Silica) | C26: =C20+C22+C23+C21 -> 685000 | D26: <-- calculation (Applicant said 700,000 to 750,000 tons)
B28: Pricing Assumptions
B29: Cement Price (2022) | C29: 134 | D29: <-- from research - https://www.ibisworld.com/us/bed/price-of-cement/190/ - need to validate with price quote from CEMEX Lyons
B30: Annual Price Increase (Cement + Transportation) | C30: 0.035 | D30: <-- Estimated Price Escalator Rate (Inflation, which is currently at 8.5% in May 2022)
B31: Net Operating Margin | C31: 0.19 | D31: <--based on CEMEX USA SEC public filings, although CEMEX Lyons could be higher/lower
B33: Transporation/Shipping Costs
B34: Miles for Shipment (from Southern Wyoming) | C34: 60 | D34: <-- estimated distance driven in miles
B35: Cost Per Ton-Mile (2022) | C35: 0.22 | D35: <-- https://www.bts.gov/content/average-freight-revenue-ton-mile | H35: http://cemexclaytonquarry.com/#s_2
B36: Cost for 80 ton, 18-wheeler, round-trip of 75 tons of raw material to and from location | C36: =C35*C34*75 -> 990 | D36: <-- calculation
B37: Increased Cost Per Ton of Raw Materials from 3rd party | C37: =0.35*40 -> 14 | D37: <-- based on simply 35% gross profit margin on Limestone or Silica, @ $40/ton
B38: Effective Price Increase Per Ton based on Transportation/Shipping | C38: =C34*C35 -> 13.2 | D38: <-- computed
B39: Relative Price Increase Per Ton based on Transporation/Shipping | C39: =C38/C29 -> 0.098507463 | D39: <-- computed
B41: Real Estate Transaction Assumptions
B42: Boulder County's Price - CEMEX Land Surrounding Plant Price Per Acre | C42: 17000 | D42: <--based on CEMEX proposal to Boulder County in 2022, escalating 2% per year
B43: Boulder County's Price - CEMEX Plant Site, Price Per Acre (60 Acres) | C43: 250000 | D43: <-- Estimate (what is fair market value per acre for General Industrial land - $250,000/acre)
B44: Boulder County's Price - Dowe Flats (208 Acre Plot) Value Per Acre | C44: 17000
B45: Boulder County's Price - Land Apprecation Rate | C45: 0.02 | D45: <-- what seems to be negotiated by Boulder County transactions
B46: Boulder County's Price - Conservation Easement Price Per Acre | C46: 2413.2535
B48: Fair Market Value - CEMEX Surrounding Plant Price Per Acre (830 Acres unencumbered) | C48: 40000 | D48: <-- Estimate (what is fair market value per acre that is NOT incumbered with a Conservation Easement)
B49: Fair Market Value - CEMEX Plant Site Land (60 Acres w/ Structures Included, zoned General Industrial) | C49: =250000 -> 250000 | D49: <-- Estimate (what is fair market value per acre for General Industrial land - $250,000/acre)
B50: Fair Market Value - CEMEX Surrounding Plant Price Per Acre (830 Acres w/ 75% Conservation Easement) | C50: 25000 | D50: <-- Estimate (what is fair market value per acre that is incumbered with a Conservation Easement
B51: Fair Market Value - CEMEX Dowe Flats (208 Acre Plot) Price Per Acre | C51: 25000 | D51: <-- Estimate (what is fair market value per acre)
B52: Fair Market Value - Land Appreciation Rate | C52: 0.075 | D52: <-- Average Annual FMV Increase
B54: Water Rights Transaction Assumptions
B55: CEMEX Water Rights (# of Acre Feet Owned) | C55: ='Water Rights'!I15 -> 10571.982 | D55: <-- Estimate based on relative ownership % of Smead Ditch and others need to find this out)
B56: CEMEX Price Per Acre Foot | C56: ='Water Rights'!K15 -> 1555.8797 | D56: <-- Estimate based on commentary from water broker (CB-T water transacts for $75,000 per Acre Foot)
B57: CEMEX Estimated Value of Water Rights (2022) | C57: =C55*C56 -> 16448732 | D57: <--computed
B58: Water Rights Appreciation Per Year | C58: 0.035
B60: Option A - Stop Mining, Operate "Plant Indefinitely" | C60: =C94 -> -3237342.5
B61: Do Nothing; Dowe Flats Shuts Down, Cement Plant Operates "Indefinitely"
B62: - CEMEX also could sell additional 208 acres of Dowe Flats in this transaction if they wish at FMV
B64: Period | C64: 0 | D64: =C64+1 -> 1 | E64: =D64+1 -> 2 | F64: =E64+1 -> 3 | G64: =F64+1 -> 4 | H64: =G64+1 -> 5 | I64: =H64+1 -> 6 | J64: =I64+1 -> 7 | K64: =J64+1 -> 8 | ... AG64: =AF64+1 -> 30
B65: Year | C65: 2022 | D65: =C65+1 -> 2023 | E65: =D65+1 -> 2024 | F65: =E65+1 -> 2025 | G65: =F65+1 -> 2026 | H65: =G65+1 -> 2027 | I65: =H65+1 -> 2028 | J65: =I65+1 -> 2029 | K65: =J65+1 -> 2030 | ... AG65: =AF65+1 -> 2052
B66: PV Times Factor | C66: =(1-$C$11)^C64 -> 1 | D66: =(1-$C$11)^D64 -> 0.855 | E66: =(1-$C$11)^E64 -> 0.731025 | F66: =(1-$C$11)^F64 -> 0.62502638 | G66: =(1-$C$11)^G64 -> 0.53439755 | H66: =(1-$C$11)^H64 -> 0.45690991 | I66: =(1-$C$11)^I64 -> 0.39065797 | J66: =(1-$C$11)^J64 -> 0.33401256 | ... AG66: =(1-$C$11)^AG64 -> 0.0090987858
B68: Investing/Real Estate Related Cash Flows
B69: Dowe Flats - 766 Acres - Operations & Development Parcel Sale to Boulder County (existing agreement) | F69: 7150000
B70: Dowe Flats - 208 Acres - Sell @ FMV in 2025 to highest bidder | F70: =208*C51*(1+C52)^F64 -> 6459943.8
B71: Dowe Flats - Reclamation Costs (spread over 24 months) | D71: =$C$14/2 -> -6341649.5 | E71: =$C$14/2 -> -6341649.5
B72: Silica Quarry - Reclamation Costs (spread over 24 months) | D72: =$C$16/3 -> -136455.33 | E72: =$C$16/3 -> -136455.33
B73: Lease Payments to Boulder County | D73: -1000 | E73: -1000 | F73: -1000
B74: Total Investing/Real Estate Related Cash Flows | D74: =SUM(D69:D73) -> -6479104.8 | E74: =SUM(E69:E73) -> -6479104.8 | F74: =SUM(F69:F73) -> 13608944 | G74: =SUM(G69:G73) -> 0 | H74: =SUM(H69:H73) -> 0 | I74: =SUM(I69:I73) -> 0 | J74: =SUM(J69:J73) -> 0 | K74: =SUM(K69:K73) -> 0 | ... AG74: =SUM(AG69:AG73) -> 0
B76: Operating Cash Flow
B77: Tons Per Year of Cement Produced | C77: =C25 -> 338475 | D77: =C77 -> 338475 | E77: =D77 -> 338475 | F77: =E77 -> 338475 | G77: =F77 -> 338475 | H77: =G77 -> 338475 | I77: =H77 -> 338475 | J77: =I77 -> 338475 | K77: =J77 -> 338475 | ... AG77: =AF77 -> 338475
B78: Avg Cement Selling Price | C78: =C29 -> 134 | D78: =C78*(1+$C$30) -> 138.69 | E78: =D78*(1+$C$30) -> 143.54415 | F78: =E78*(1+$C$30) -> 148.5682 | G78: =F78*(1+$C$30) -> 153.76808 | H78: =G78*(1+$C$30) -> 159.14997 | I78: =H78*(1+$C$30) -> 164.72021 | J78: =I78*(1+$C$30) -> 170.48542 | K78: =J78*(1+$C$30) -> 176.45241 | ... AG78: =AF78*(1+$C$30) -> 376.11036
B79: Total Operating Cash Flows | C79: =C77*C78 -> 45355650 | D79: =D77*D78 -> 46943098 | E79: =E77*E78 -> 48586106 | F79: =F77*F78 -> 50286620 | G79: =G77*G78 -> 52046652 | H79: =H77*H78 -> 53868284 | I79: =I77*I78 -> 55753674 | J79: =J77*J78 -> 57705053 | ... AG79: =AG77*AG78 -> 1.2730395e+08
B81: EBITDA Margin (before Transport and 3rd Party Purchase Costs) | C81: =C31 -> 0.19 | D81: =C81 -> 0.19 | E81: =D81 -> 0.19 | F81: =E81 -> 0.19 | G81: =F81 -> 0.19 | H81: =G81 -> 0.19 | I81: =H81 -> 0.19 | J81: =I81 -> 0.19 | K81: =J81 -> 0.19 | ... AG81: =AF81 -> 0.19
B82: Net Cash Flow | C82: =C79*C81 -> 8617573.5 | D82: =D79*D81 -> 8919188.6 | E82: =E79*E81 -> 9231360.2 | F82: =F79*F81 -> 9554457.8 | G82: =G79*G81 -> 9888863.8 | H82: =H79*H81 -> 10234974 | I82: =I79*I81 -> 10593198 | J82: =J79*J81 -> 10963960 | ... AG82: =AG79*AG81 -> 24187751
B84: Adjustments - Shipment + 3rd Party Cash Flows
B85: Tons of Raw Materials Shipped/Imported vs Base Case | C85: =(C22+C21)*0.25 -> 100000 | D85: =C21+C22 -> 400000 | E85: =D85 -> 400000 | F85: =E85 -> 400000 | G85: =F85 -> 400000 | H85: =G85 -> 400000 | I85: =H85 -> 400000 | J85: =I85 -> 400000 | K85: =J85 -> 400000 | L85: =K85 -> 400000 | ... AG85: =AF85 -> 400000
B86: Per Ton Price Increase. | C86: =$C$37*(1+$C$30)^C64 -> 14 | D86: =$C$37*(1+$C$30)^D64 -> 14.49 | E86: =$C$37*(1+$C$30)^E64 -> 14.99715 | F86: =$C$37*(1+$C$30)^F64 -> 15.52205 | G86: =$C$37*(1+$C$30)^G64 -> 16.065322 | H86: =$C$37*(1+$C$30)^H64 -> 16.627608 | I86: =$C$37*(1+$C$30)^I64 -> 17.209575 | J86: =$C$37*(1+$C$30)^J64 -> 17.81191 | ... AG86: =$C$37*(1+$C$30)^AG64 -> 39.295112
B87: Increased Price Paid Per Ton (3rd Party) | C87: =C85*C86 -> 1400000 | D87: =D85*$C$37 -> 5600000 | E87: =E85*$C$37 -> 5600000 | F87: =F85*$C$37 -> 5600000 | G87: =G85*$C$37 -> 5600000 | H87: =H85*$C$37 -> 5600000 | I87: =I85*$C$37 -> 5600000 | J87: =J85*$C$37 -> 5600000 | K87: =K85*$C$37 -> 5600000 | ... AG87: =AG85*$C$37 -> 5600000
B88: Shipping Cost Per Ton-Mile | C88: =C35 -> 0.22 | D88: =C88*(1+$C$30) -> 0.2277 | E88: =D88*(1+$C$30) -> 0.2356695 | F88: =E88*(1+$C$30) -> 0.24391793 | G88: =F88*(1+$C$30) -> 0.25245506 | H88: =G88*(1+$C$30) -> 0.26129099 | I88: =H88*(1+$C$30) -> 0.27043617 | J88: =I88*(1+$C$30) -> 0.27990144 | K88: =J88*(1+$C$30) -> 0.28969799 | ... AG88: =AF88*(1+$C$30) -> 0.61749462
B89: Additional Shipping Cost for Trucking In Raw Materials | C89: =C85*C88*$C$34 -> 1320000 | D89: =D85*D88*$C$34 -> 5464800 | E89: =E85*E88*$C$34 -> 5656068 | F89: =F85*F88*$C$34 -> 5854030.4 | G89: =G85*G88*$C$34 -> 6058921.4 | H89: =H85*H88*$C$34 -> 6270983.7 | I89: =I85*I88*$C$34 -> 6490468.1 | J89: =J85*J88*$C$34 -> 6717634.5 | ... AG89: =AG85*AG88*$C$34 -> 14819871
B91: Adjusted Net Cash Flow | C91: =C74+C82-(C87+C89) -> 5897573.5 | D91: =D74+D82-(D87+D89) -> -8624716.3 | E91: =E74+E82-(E87+E89) -> -8503812.7 | F91: =F74+F82-(F87+F89) -> 11709371 | G91: =G74+G82-(G87+G89) -> -1770057.6 | H91: =H74+H82-(H87+H89) -> -1636009.7 | I91: =I74+I82-(I87+I89) -> -1497270 | J91: =J74+J82-(J87+J89) -> -1353674.4 | ... AG91: =AG74+AG82-(AG87+AG89) -> 3767880.3
B92: PV Cash Flow | C92: =C91*C66 -> 5897573.5 | D92: =D91*D66 -> -7374132.4 | E92: =E91*E66 -> -6216499.7 | F92: =F91*F66 -> 7318665.8 | G92: =G91*G66 -> -945914.47 | H92: =H91*H66 -> -747509.02 | I92: =I91*I66 -> -584920.46 | J92: =J91*J66 -> -452144.27 | ... AG92: =AG91*AG66 -> 34283.136
B94: NPV | C94: {=NPV(C11,C91:AG91)} -> -3237342.5
B95: Boulder County Spends | C95: =F69 -> 7150000
B100: Option B - Operate 15 Years, then Shut Down, Sell to BoCo | C100: =C131 -> 64432187
B101: Proposal Dowe Flats Extended 15 Years, Plant Shuts Down in 15 years, followed by reclamation; Sell Land Surroudning Plant to Boulder County; Sell Plant to Someone Else
B103: Period | C103: 0 | D103: =C103+1 -> 1 | E103: =D103+1 -> 2 | F103: =E103+1 -> 3 | G103: =F103+1 -> 4 | H103: =G103+1 -> 5 | I103: =H103+1 -> 6 | J103: =I103+1 -> 7 | K103: =J103+1 -> 8 | ... AG103: =AF103+1 -> 30
B104: Year | C104: 2022 | D104: =C104+1 -> 2023 | E104: =D104+1 -> 2024 | F104: =E104+1 -> 2025 | G104: =F104+1 -> 2026 | H104: =G104+1 -> 2027 | I104: =H104+1 -> 2028 | J104: =I104+1 -> 2029 | K104: =J104+1 -> 2030 | ... AG104: =AF104+1 -> 2052
B105: PV Times Factor | C105: =(1-$C$11)^C103 -> 1 | D105: =(1-$C$11)^D103 -> 0.855 | E105: =(1-$C$11)^E103 -> 0.731025 | F105: =(1-$C$11)^F103 -> 0.62502638 | G105: =(1-$C$11)^G103 -> 0.53439755 | H105: =(1-$C$11)^H103 -> 0.45690991 | I105: =(1-$C$11)^I103 -> 0.39065797 | J105: =(1-$C$11)^J103 -> 0.33401256 | ... AG105: =(1-$C$11)^AG103 -> 0.0090987858
B107: Investing/Real Estate Cash Flows
B108: Dowe Flats - Rental Payments to Boulder County | D108: -400000 | E108: -400000 | F108: -400000 | G108: -400000 | H108: -400000 | I108: -400000 | J108: -400000 | K108: -400000 | L108: -400000 | M108: -400000 | N108: -400000 | O108: -400000 | P108: -400000 | Q108: -400000 | R108: -400000 | S108: -1000 | T108: -1000 | U108: -1000 | V108: 0 | W108: 0
B109: Sale of Plant Parcel in 2041 to Boulder County (830 Acres) | V109: =830*(1+C45)^(V103-1)*$C$42 -> 20152555
B110: Sale of Plant in 2041 @ FMV | V110: =60*C43*(1+C52)^V103 -> 59272341
B111: Sale of ALL CEMEX Water Rights | V111: =$C$55*$C$56*(1+C58)^V103 -> 31622708
B113: Reclamation Costs
B114: Reclamation Costs (Dowe Flats) - from 2038 to 2040 | S114: =($C$14/3)*(1+$C$30)^S$103 -> -7330887.8 | T114: =($C$14/3)*(1+$C$30)^T103 -> -7587468.9 | U114: =($C$14/3)*(1+$C$30)^U103 -> -7853030.3
B115: Reclamation Costs (Plant Land, but NOT Plant from 2038 to 2040 | S115: =$C$15/3*(1+$C$30)^S$103 -> -5174865.7 | T115: =$C$15/3*(1+$C$30)^S$103 -> -5174865.7 | U115: =$C$15/3*(1+$C$30)^S$103 -> -5174865.7
B116: Reclamation Costs (Silica Quarry - in 2023 and 2024 | D116: =$C$16/2 -> -204683 | E116: =$C$16/2 -> -204683
B117: Total Real Estate Cash Flows | D117: =SUM(D108:D116) -> -604683 | E117: =SUM(E108:E116) -> -604683 | F117: =SUM(F108:F116) -> -400000 | G117: =SUM(G108:G116) -> -400000 | H117: =SUM(H108:H116) -> -400000 | I117: =SUM(I108:I116) -> -400000 | J117: =SUM(J108:J116) -> -400000 | K117: =SUM(K108:K116) -> -400000 | ... W117: =SUM(W108:W116) -> 0
B119: Operating Cash Flow
B120: Tons Per Year of Cement Produced and Sold | C120: =C25 -> 338475 | D120: =C120 -> 338475 | E120: =D120 -> 338475 | F120: =E120 -> 338475 | G120: =F120 -> 338475 | H120: =G120 -> 338475 | I120: =H120 -> 338475 | J120: =I120 -> 338475 | K120: =J120 -> 338475 | ... R120: =Q120 -> 338475 | S120: 0 | T120: 0 | U120: 0 | V120: 0 | W120: 0
B121: Avg Cement Price | C121: =C29 -> 134 | D121: =C121*(1+$C$30) -> 138.69 | E121: =D121*(1+$C$30) -> 143.54415 | F121: =E121*(1+$C$30) -> 148.5682 | G121: =F121*(1+$C$30) -> 153.76808 | H121: =G121*(1+$C$30) -> 159.14997 | I121: =H121*(1+$C$30) -> 164.72021 | J121: =I121*(1+$C$30) -> 170.48542 | K121: =J121*(1+$C$30) -> 176.45241 | ... W121: =V121*(1+$C$30) -> 266.63171
B122: Total Revenue | C122: =C120*C121 -> 45355650 | D122: =D120*D121 -> 46943098 | E122: =E120*E121 -> 48586106 | F122: =F120*F121 -> 50286620 | G122: =G120*G121 -> 52046652 | H122: =H120*H121 -> 53868284 | I122: =I120*I121 -> 55753674 | J122: =J120*J121 -> 57705053 | ... W122: =W120*W121 -> 0
B124: EBITDA Margin | C124: =$C$31 -> 0.19 | D124: =C124 -> 0.19 | E124: =D124 -> 0.19 | F124: =E124 -> 0.19 | G124: =F124 -> 0.19 | H124: =G124 -> 0.19 | I124: =H124 -> 0.19 | J124: =I124 -> 0.19 | K124: =J124 -> 0.19 | ... T124: =S124 -> 0.19
B125: Net Cash Flow | C125: =C122*C124 -> 8617573.5 | D125: =D122*D124 -> 8919188.6 | E125: =E122*E124 -> 9231360.2 | F125: =F122*F124 -> 9554457.8 | G125: =G122*G124 -> 9888863.8 | H125: =H122*H124 -> 10234974 | I125: =I122*I124 -> 10593198 | J125: =J122*J124 -> 10963960 | ... W125: =W122*W124 -> 0
B128: Adjusted Net Cash Flow | C128: =C125+C117 -> 8617573.5 | D128: =D125+D117 -> 8314505.6 | E128: =E125+E117 -> 8626677.2 | F128: =F125+F117 -> 9154457.8 | G128: =G125+G117 -> 9488863.8 | H128: =H125+H117 -> 9834974 | I128: =I125+I117 -> 10193198 | J128: =J125+J117 -> 10563960 | ... X128: =X125+X117 -> 0
B129: PV Cash Flow | C129: =C128*C105 -> 8617573.5 | D129: =D128*D105 -> 7108902.3 | E129: =E128*E105 -> 6306316.7 | F129: =F128*F105 -> 5721777.6 | G129: =G128*G105 -> 5070825.6 | H129: =H128*H105 -> 4493697.1 | I129: =I128*I105 -> 3982054.1 | J129: =J128*J105 -> 3528495.4 | ... X129: =X128*X105 -> 0
...

Sheet Proposal Matrix
B2: Key Deal Terms & Benefits | C2: Option A Status Quo "Possibly Indefinite" | D2: Option B CEMEX Proposal "15 Years More Mining" | E2: Option C Town of Lyons Proposal "5 Years More Mining" | F2: Option D (CEMEX's BATNA) CEMEX Stops Production, Sells Assets to Highest Bidder
B4: CEMEX Gets:
B5: - Dowe Flats Mining Extension | C5: 0 Years | D5: 15 Years | E5: 5 Years
B6: - Continued Plant Operation | C6: Permitted Indefinitely | D6: 15 Years | E6: 5 Years
B7: - Estimated Net Present Value for CEMEX (e.g. Value for Shareholders) | C7: ='NPVs & Pro-Formas'!C3 -> -3237342.5 | D7: ='NPVs & Pro-Formas'!C4 -> 64432187 | E7: ='NPVs & Pro-Formas'!C5 -> 40720124 | F7: =#REF! -> #REF!
B8: - Profitable & Sustainable Ongoing Operation | C8: No | D8: Yes | E8: Yes | F8: No
B9: - NEW: Graceful Exit and Wind Down from Boulder County | C9: No | D9: No | E9: Yes | F9: No
B11: CEMEX Gives:
B12: - Purchase Options @ $17,000/acre on Land Surrounding Plant (830 Acres) | C12: No | D12: Yes - to Boulder County | E12: Yes - to Boulder (~60%), Lyons (~40%)
B13: - NEW: Purchase Options @ $17,000/acre on remaining CEMEX Area incl Plant (~100 Acres) | C13: No | D13: No | E13: Yes - to Lyons
B14: - NEW: Updated IGA for Land Use (Covenant / Conservation Easement) on CEMEX Area (930 Acres) | C14: No | D14: No | E14: Yes - w/ Boulder County & Lyons
B15: - NEW: Commitment to Close Plant | C15: No | D15: Yes - by 2037 | E15: Yes - by 2027
B16: - NEW: Demolish Plant and Perform Cleanup/Reclamation | C16: Indeterminate | D16: Indeterminate | E16: by 2030
B17: - Reclaim Dowe Flats | C17: by 2025 | D17: by 2041 | E17: by 2030
B18: - Reclaim Land surrounding Plant | C18: Indeterminate | D18: by 2041 | E18: by 2030
B19: - Provide Trail Easement for St Vrain Greenway | C19: No | D19: Yes | E19: Yes
B20: - NEW: Commitment best attempts to sequester C02 Emissions | C20: No | D20: No | E20: Yes
B21: - NEW: Commitment best attempts to mitigate ongoing Noise, Light & Dust pollution | C21: No | D21: No | E21: Yes
B22: - NEW: Lyons and/or Boulder County Right of First Refusal on Any Water Rights Sales | C22: No | D22: No | E22: Yes
B24: Boulder County Gets:
B25: -NEW: Climate Goals: Annual Reduction of C02 by 2030 | C25: 0 | D25: 0 | E25: 357,000 Tons/Yr (12.5% of 2030 Goal) | F25: 350,000 Tons (12.5% of 2030 Goal)
B26: - Addtl Acres of Protected Open Space and/or Conserved Land | C26: =SUM(C27:C28) -> 766 | D26: =SUM(D27:D28) -> 1804 | E26: =SUM(E27:E28) -> 1904 | F26: =SUM(F27:F28) -> 766
B27: - Addtl Acres of Open Space | C27: 766 | D27: 1804 | E27: =766+208+510 -> 1484 | F27: 766
B28: - NEW: Addtl Acres governed by Covenenant / Conservation Easement (75% minimum CE) | C28: 0 | D28: 0 | E28: 420 | F28: 0
B29: - Total Amount Spent | C29: 7150000 | D29: 8000000 | E29: ='NPVs & Pro-Formas'!C175 -> 3840400
B30: - NEW: Updated IGA for Land Use (Covenant / Conservation Easement) on entire CEMEX Area (930 Acres) | C30: No | D30: No - 830 Acres | E30: Yes - 930 Acres
B31: - Purchase Options to acquire ~510 Acres Open Space @ $17,000 / acre | C31: No | D31: Yes - 830 Acres | E31: Yes - 510 Acres
B32: - NEW: Purchase Options to acquire ~420 Acres CEMEX Area after 2035 if not Exercised/Annexed by Lyons | C32: No | D32: No | E32: Yes
B33: - Cement Plant Closes (*) | C33: No | D33: Yes (2037) | E33: Yes (2027) | F33: No
B34: - NEW: Cessation of General Industrial Activity at CEMEX Plant Site and Zoning Change | C34: No | D34: No | E34: Yes (2030) | F34: No
B35: - NEW: Plant Demolished and Plant Site Cleaned Up | C35: No | D35: No | E35: Yes (2030) | F35: No
B36: - NEW: Improved Beauty of St. Vrain Valley / "Gateway to the Rockies" | C36: No | D36: No | E36: Yes | F36: No
B37: - Trail Easement for St Vrain Greenway | C37: No | D37: Yes | E37: Yes
B38: - Access Easement to Boulder County property | C38: No | D38: Yes | E38: Yes
B39: - NEW Credit/Accolades for Transforming a Brown Field Into a Best-In-Class Eco Community | C39: No | D39: No | E39: Yes
B41: Town of Lyons Gets
B42: - NEW: Updated IGA for Land Use (Covenant / Conservation Easement) on entire CEMEX Area (930 Acres) | C42: No | D42: No - 830 Acres | E42: Yes - 930 Acres
B43: - Options to Develop portion of CEMEX Area for Low-Density Sustainable Mixed-Use (spirit of 2012 IGA) | C43: No | D43: No | E43: Yes | F43: No
B44: - Options to Develop Municipal Facility for 100% Renewable Energy (spirit of 2012 IGA) | C44: No | D44: No | E44: Yes
B45: - NEW: Purchase Options & 5yr window to Annex/Solicit Plans for ~420 Acres CEMEX Area (2030 to 2035) @ $17,000 per acre | C45: No | D45: No | E45: Yes
B46: - NEW: Ability to engage/sollicit Sustainable Investment Community for Bids/Proposals | C46: No | D46: No | E46: Yes
B47: - Boulder County assistance/cooperation with Sustainable Development Proposals for CEMEX Area (from 2012 IGA) | C47: Yes | D47: Yes | E47: Yes
B48: - NEW: Potential Increase in Town Tax Revenue Base | C48: No | D48: No | E48: Yes | F48: No
B49: - NEW: Viable & Sustainable Eastern Corridor | C49: No | D49: No | E49: Yes | F49: No
B50: - NEW: Cessation of General Industrial Activity at CEMEX Plant Site | C50: No | D50: No | E50: Yes | F50: No
B52: For Community:
B53: - NEW: Plant Goes Away, Forever. | C53: No | D53: No | E53: Yes | F53: No
B54: - NEW: Climate Goals: Annual Reduction of C02 by 2030 | C54: 0 | D54: 0 | E54: 357,000 Tons/Yr (12.5% of 2030 Goal) | F54: 350,000 Tons (12.5% of 2030 Goal)
B55: - NEW: Reduced Noise, Light & Dust Pollution | C55: No | D55: No | E55: Yes | F55: No
B56: - Beautiful Walking/Biking Trails through the St. Vrain Greenway | C56: No | D56: Yes | E56: Yes | F56: No
B57: - Dowe Flats 1600 Acres as Open Space | C57: Yes - 2025 | D57: Yes - 2040 | E57: Yes - 2030 | F57: Yes
B58: - NEW: Entirety of CEMEX Plant Land (930 Acres) becomes Protected/Conserved | C58: No | D58: No | E58: Yes | F58: No
B59: - NEW: Pedistrian Bridge connecting Dowe Flats to CEMEX Plant Land | C59: No | D59: No | E59: Yes | F59: No
B60: - Ongoing $40K/year donations/gifts from CEMEX | C60: Yes | D60: Yes | E60: No | F60: No

Sheet Water Rights
F1: 1 cfs = | G1: 1.9834711 | H1: acre-feet per day
B2: Source: 1977 Lyons Plant Reclamation Plan - Permit M77208
F3: unit | G3: days a year available | I3: acre-feet/yr equivalent | K3: acre-foot pricing / market | L3: value
B4: 1. Outlet ditch and outlet pipeline | E4: 6.4 | F4: cfs | G4: =180 -> 180 | I4: =E4*$G$1*G4 -> 2284.9587 | K4: 1000 | L4: =I4*K4 -> 2284958.7
B5: 2. Martin Marietta east seepage ditch | E5: 1 | F5: cfs | G5: =180 -> 180 | I5: =E5*$G$1*G5 -> 357.0248 | K5: 1000 | L5: =I5*K5 -> 357024.8
B6: 3. Martin Marietta tile drain | E6: 1.5 | F6: cfs | G6: =180 -> 180 | I6: =E6*$G$1*G6 -> 535.5372 | K6: 1000 | L6: =I6*K6 -> 535537.2
B7: 4. Martin Marietta cement lake | C7: *(stoarage and recreational)(= | E7: 36 | F7: acre-feet | G7: 365 | K7: 0 | L7: =I7*K7 -> 0
B8: 5. Kimball Lake | E8: 20 | F8: acre-feet | G8: 365 | K8: 0 | L8: =I8*K8 -> 0
B9: 6. Smead Ditch | E9: 4 | F9: cfs | G9: 180 | I9: =E9*$G$1*G9 -> 1428.0992 | K9: 1000 | L9: =I9*K9 -> 1428099.2
B10: 7. Swede Ditch | E10: 1.675 | F10: cfs | G10: 180 | I10: =E10*$G$1*G10 -> 598.01654 | K10: 1000 | L10: =I10*K10 -> 598016.54
B11: 8. South Ledge | E11: 14.32 | F11: cfs | G11: 180 | I11: =E11*$G$1*G11 -> 5112.5951 | K11: 1000 | L11: =I11*K11 -> 5112595.1
B12: 9. Big Thompson water | E12: 55 | F12: acre-feet | G12: 1 | I12: =E12*G12 -> 55 | K12: 75000 | L12: =I12*K12 -> 4125000
B13: 10. Dowe Flats Water (1993 Permit) | E13: 150000 | F13: gallons-day | G13: 1 | I13: =0.55*365 -> 200.75 | K13: 10000 | L13: =I13*K13 -> 2007500
B15: Totals | I15: =SUM(I4:I13) -> 10571.982 | K15: =L15/I15 -> 1555.8797 | L15: =SUM(L4:L13) -> 16448732
